LICENSE
MANIFEST.in
README.rst
buildout.cfg
develop.cfg
pyproject.toml
requirements.txt
setup.py
version.txt
bob/__init__.py
bob.db.mnist.egg-info/PKG-INFO
bob.db.mnist.egg-info/SOURCES.txt
bob.db.mnist.egg-info/dependency_links.txt
bob.db.mnist.egg-info/entry_points.txt
bob.db.mnist.egg-info/not-zip-safe
bob.db.mnist.egg-info/requires.txt
bob.db.mnist.egg-info/top_level.txt
bob/db/__init__.py
bob/db/mnist/__init__.py
bob/db/mnist/driver.py
bob/db/mnist/files.txt
bob/db/mnist/query.py
bob/db/mnist/test.py
doc/conf.py
doc/guide.rst
doc/index.rst
doc/py_api.rst